antimalone/__init__.py
antimalone/adaptive_analysis.py
antimalone/anomaly_detection.py
antimalone/context_hashing.py
antimalone/entropy.py
antimalone/fuzzy_hashing.py
antimalone/indexing.py
antimalone/obfuscation_detection.py
ANTIMALONE-0.1.1.dist-info/METADATA
ANTIMALONE-0.1.1.dist-info/WHEEL
ANTIMALONE-0.1.1.dist-info/top_level.txt
ANTIMALONE-0.1.1.dist-info/RECORD
