Metadata-Version: 2.1
Name: ANTIMALONE
Version: 0.1.1
Summary: A novel antivirus engine with advanced static analysis algorithms.
Home-page: https://github.com/codewithjoymondal
Author: Joy mondal
Author-email: contact.joymondal@gmail.com
Classifier: Programming Language :: Python :: 3
Classifier: License :: OSI Approved :: MIT License
Classifier: Operating System :: OS Independent
Requires-Python: >=3.6
Requires-Dist: keras
Requires-Dist: networkx
Requires-Dist: numpy
Requires-Dist: scikit-learn
